source_monday/__init__.py
source_monday/extractor.py
source_monday/graphql_requester.py
source_monday/item_pagination_strategy.py
source_monday/manifest.yaml
source_monday/run.py
source_monday/schemas/activity_logs.json
source_monday/schemas/boards.json
source_monday/schemas/items.json
source_monday/schemas/tags.json
source_monday/schemas/teams.json
source_monday/schemas/updates.json
source_monday/schemas/users.json
source_monday/schemas/workspaces.json
source_monday/source.py
source_monday/spec.json
source_monday/state_migration.py
source_monday/transformation.py
airbyte_source_monday-2.3.1.dist-info/METADATA
airbyte_source_monday-2.3.1.dist-info/WHEEL
airbyte_source_monday-2.3.1.dist-info/entry_points.txt
airbyte_source_monday-2.3.1.dist-info/RECORD
