Metadata-Version: 2.3
Name: airbyte-source-monday
Version: 2.3.1
Summary: Source implementation for Monday.
License: MIT
Author: Airbyte
Author-email: contact@airbyte.io
Requires-Python: >=3.10,<3.12
Classifier: License :: OSI Approved :: MIT License
Classifier: Programming Language :: Python :: 3
Classifier: Programming Language :: Python :: 3.10
Classifier: Programming Language :: Python :: 3.11
Requires-Dist: airbyte_cdk (>=6,<7)
Project-URL: Documentation, https://docs.airbyte.com/integrations/sources/monday
Project-URL: Homepage, https://airbyte.com
Project-URL: Repository, https://github.com/airbytehq/airbyte
